main.py
mcp_miaocontrol_v7-0.1.7.dist-info/METADATA
mcp_miaocontrol_v7-0.1.7.dist-info/WHEEL
mcp_miaocontrol_v7-0.1.7.dist-info/entry_points.txt
mcp_miaocontrol_v7-0.1.7.dist-info/top_level.txt
mcp_miaocontrol_v7-0.1.7.dist-info/RECORD
