Metadata-Version: 2.4
Name: mcp_MiaoControl_v7
Version: 0.1.7
Summary: 让控制变得简单!
Requires-Python: >=3.11
Requires-Dist: build>=1.2.2.post1
Requires-Dist: httpx[http2]>=0.28.1
Requires-Dist: mcp>=1.8.0
Requires-Dist: requests>=2.32.3
Requires-Dist: twine>=6.1.0
